funcsfreq/__init__.py
funcsfreq/setup.py
funcsfreq/odps/__init__.py
funcsfreq/odps/funcs.py
funcsfreq/odps_passvar/__init__.py
funcsfreq/odps_passvar/funcs.py
funcsfreq/selfdev/__init__.py
funcsfreq/selfdev/funcs.py
funcsfreq-0.0.3.5.dist-info/METADATA
funcsfreq-0.0.3.5.dist-info/WHEEL
funcsfreq-0.0.3.5.dist-info/top_level.txt
funcsfreq-0.0.3.5.dist-info/RECORD
